python_http_client/VERSION.txt
python_http_client/__init__.py
python_http_client/client.py
python_http_client/exceptions.py
python_http_client-3.3.6.dist-info/LICENSE
python_http_client-3.3.6.dist-info/METADATA
python_http_client-3.3.6.dist-info/WHEEL
python_http_client-3.3.6.dist-info/top_level.txt
python_http_client-3.3.6.dist-info/RECORD
