Metadata-Version: 2.1
Name: python_http_client
Version: 3.3.6
Summary: HTTP REST client, simplified for Python
Home-page: https://github.com/sendgrid/python-http-client
Author: Elmer Thomas
Author-email: help@twilio.com
License: MIT
Download-URL: https://github.com/sendgrid/python-http-client/tarball/3.3.6
Keywords: REST,HTTP,API
Platform: UNKNOWN
Classifier: Programming Language :: Python :: 2.7
Classifier: Programming Language :: Python :: 3
Classifier: Programming Language :: Python :: 3.4
Classifier: Programming Language :: Python :: 3.5
Classifier: Programming Language :: Python :: 3.6
Classifier: Programming Language :: Python :: 3.7
Classifier: Programming Language :: Python :: 3.8
Classifier: Programming Language :: Python :: 3.9
Classifier: Programming Language :: Python :: 3.10
Requires-Python: >=2.7, !=3.0.*, !=3.1.*, !=3.2.*, !=3.3.*
License-File: LICENSE
